README.md
setup.py
ultocr/__init__.py
ultocr/inference.py
ultocr.egg-info/PKG-INFO
ultocr.egg-info/SOURCES.txt
ultocr.egg-info/dependency_links.txt
ultocr.egg-info/requires.txt
ultocr.egg-info/top_level.txt
ultocr/loader/__init__.py
ultocr/loader/augment.py
ultocr/loader/base.py
ultocr/loader/create_lmdb_data.py
ultocr/loader/create_train_val_data.py
ultocr/loader/detection/__init__.py
ultocr/loader/detection/det_loader.py
ultocr/loader/detection/make_bordermap.py
ultocr/loader/detection/make_segmap.py
ultocr/loader/recognition/__init__.py
ultocr/loader/recognition/reg_loader.py
ultocr/loader/recognition/translate.py
ultocr/logger/__init__.py
ultocr/logger/logger.py
ultocr/model/__init__.py
ultocr/model/loss.py
ultocr/model/lr_scheduler.py
ultocr/model/common/__init__.py
ultocr/model/common/context_block.py
ultocr/model/common/resnet.py
ultocr/model/common/resnet_dcn.py
ultocr/model/common/resnet_master.py
ultocr/model/common/transformer.py
ultocr/model/common/dcn/__init__.py
ultocr/model/common/dcn/setup.py
ultocr/model/common/dcn/functions/__init__.py
ultocr/model/common/dcn/functions/deform_conv.py
ultocr/model/common/dcn/functions/deform_pool.py
ultocr/model/common/dcn/modules/__init__.py
ultocr/model/common/dcn/modules/deform_conv.py
ultocr/model/common/dcn/modules/deform_pool.py
ultocr/model/detection/__init__.py
ultocr/model/detection/db_net.py
ultocr/model/detection/head.py
ultocr/model/detection/postprocess.py
ultocr/model/detection/segout.py
ultocr/model/kie/__init__.py
ultocr/model/kie/encoder.py
ultocr/model/kie/graph.py
ultocr/model/kie/pick.py
ultocr/model/recognition/__init__.py
ultocr/model/recognition/master.py
ultocr/model/recognition/postprocess.py
ultocr/utils/__init__.py
ultocr/utils/box_utils.py
ultocr/utils/det_utils.py
ultocr/utils/download.py
ultocr/utils/utils_function.py
ultocr/utils/visualize.py