Metadata-Version: 2.1
Name: ultocr
Version: 0.3.0
Summary: text detection + text recognition
Home-page: https://github.com/cuongngm/text-in-image
Author: cuongngm
Author-email: cuonghip0908@gmail.com
License: UNKNOWN
Platform: UNKNOWN
Classifier: Programming Language :: Python :: 3
Classifier: License :: OSI Approved :: MIT License
Classifier: Operating System :: OS Independent
Requires-Python: >=3.6
